markdowntodocx/__init__.py
markdowntodocx/markdownconverter.py
markdowntodocx-0.1.9.2.dist-info/licenses/LICENSE
markdowntodocx-0.1.9.2.dist-info/METADATA
markdowntodocx-0.1.9.2.dist-info/WHEEL
markdowntodocx-0.1.9.2.dist-info/top_level.txt
markdowntodocx-0.1.9.2.dist-info/RECORD
