Metadata-Version: 2.4
Name: markdowntodocx
Version: 0.1.9.2
Summary: Convert markdown inside Docx to docx styles
Home-page: https://github.com/fbarre96/MarkDownToDocxStyle
Author: Fabien Barre
License: MIT
License-File: LICENSE
Requires-Dist: python-docx>=1.1.2
Requires-Dist: requests
Requires-Dist: pygments
Dynamic: author
Dynamic: description
Dynamic: description-content-type
Dynamic: home-page
Dynamic: license
Dynamic: license-file
Dynamic: requires-dist
Dynamic: summary
